xliff_ai_translator/__init__.py
xliff_ai_translator/main.py
xliff_ai_translator-1.0.dist-info/LICENSE
xliff_ai_translator-1.0.dist-info/METADATA
xliff_ai_translator-1.0.dist-info/WHEEL
xliff_ai_translator-1.0.dist-info/entry_points.txt
xliff_ai_translator-1.0.dist-info/top_level.txt
xliff_ai_translator-1.0.dist-info/RECORD
