Metadata-Version: 2.1
Name: xliff-ai-translator
Version: 1.0
Summary: AI-driven solution for efficient XLIFF/XLF file translation , bridging the gap between languages for localized content.
Home-page: https://github.com/sutasrof/Xliff-AI-Translator
Author: sutasrof
Author-email: mario.chauvet@icloud.com
Classifier: Programming Language :: Python :: 3
Classifier: License :: OSI Approved :: GNU General Public License v3 or later (GPLv3+)
Classifier: Operating System :: OS Independent
Requires-Python: >=3.6
License-File: LICENSE
Requires-Dist: transformers[torch] >=4.34.1
Requires-Dist: sentencepiece >=0.1.99
Requires-Dist: lxml >=4.9.3
